edf_plasma_dissectors/__init__.py
edf_plasma_dissectors/__version__.py
edf_plasma_dissectors/android/__init__.py
edf_plasma_dissectors/android/mvt/__init__.py
edf_plasma_dissectors/android/mvt/appops.py
edf_plasma_dissectors/android/mvt/files.py
edf_plasma_dissectors/android/mvt/packages.py
edf_plasma_dissectors/android/mvt/packages_perms.py
edf_plasma_dissectors/android/mvt/processes.py
edf_plasma_dissectors/android/mvt/sms.py
edf_plasma_dissectors/elf/__init__.py
edf_plasma_dissectors/elf/ctor_dtor.py
edf_plasma_dissectors/elf/export.py
edf_plasma_dissectors/elf/helper.py
edf_plasma_dissectors/elf/import_.py
edf_plasma_dissectors/elf/info.py
edf_plasma_dissectors/elf/library.py
edf_plasma_dissectors/elf/section.py
edf_plasma_dissectors/elf/segment.py
edf_plasma_dissectors/generic/__init__.py
edf_plasma_dissectors/generic/chromium.py
edf_plasma_dissectors/generic/firefox.py
edf_plasma_dissectors/generic/helper.py
edf_plasma_dissectors/generic/ssh_pub_key.py
edf_plasma_dissectors/ios/__init__.py
edf_plasma_dissectors/ios/mvt/__init__.py
edf_plasma_dissectors/ios/mvt/analytics_ad_daily.py
edf_plasma_dissectors/ios/mvt/apps.py
edf_plasma_dissectors/ios/mvt/datausage.py
edf_plasma_dissectors/ios/mvt/manifest.py
edf_plasma_dissectors/ios/mvt/safari_history.py
edf_plasma_dissectors/ios/mvt/safari_state.py
edf_plasma_dissectors/ios/mvt/shortcuts.py
edf_plasma_dissectors/ios/mvt/sms.py
edf_plasma_dissectors/ios/mvt/tcc.py
edf_plasma_dissectors/ios/mvt/webkit_rsrc_load.py
edf_plasma_dissectors/ios/mvt/whatsapp.py
edf_plasma_dissectors/ios/sysdiag/__init__.py
edf_plasma_dissectors/ios/sysdiag/bluetooth.py
edf_plasma_dissectors/ios/sysdiag/disk.py
edf_plasma_dissectors/ios/sysdiag/mount.py
edf_plasma_dissectors/ios/sysdiag/process.py
edf_plasma_dissectors/ios/sysdiag/remotectl.py
edf_plasma_dissectors/ios/sysdiag/shutdown.py
edf_plasma_dissectors/ios/sysdiag/wifi.py
edf_plasma_dissectors/linux/__init__.py
edf_plasma_dissectors/linux/auditd.py
edf_plasma_dissectors-1.0.0.dist-info/licenses/LICENSE
edf_plasma_dissectors-1.0.0.dist-info/METADATA
edf_plasma_dissectors-1.0.0.dist-info/WHEEL
edf_plasma_dissectors-1.0.0.dist-info/top_level.txt
edf_plasma_dissectors-1.0.0.dist-info/RECORD
