Metadata-Version: 2.4
Name: edf-plasma-dissectors
Version: 1.0.0
Summary: EDF Plasma Dissectors
Author-email: CERT-EDF <cert@edf.fr>
License-Expression: MIT
Project-URL: Homepage, https://github.com/cert-edf/plasma
Project-URL: Repository, https://github.com/cert-edf/plasma
Project-URL: Bug Tracker, https://github.com/cert-edf/plasma/issues
Keywords: edf,plasma,forensic,artifact,dissector,normalizer,framework
Classifier: Development Status :: 5 - Production/Stable
Classifier: Intended Audience :: End Users/Desktop
Classifier: Operating System :: POSIX :: Linux
Classifier: Programming Language :: Python :: 3
Classifier: Programming Language :: Python :: 3 :: Only
Classifier: Topic :: Utilities
Classifier: Topic :: Security
Requires-Python: >=3.12
License-File: LICENSE
Requires-Dist: edf-plasma-core~=1.0
Requires-Dist: scapy~=2.5
Requires-Dist: lief~=0.14
Requires-Dist: systemd-python
Requires-Dist: construct~=2.10
Requires-Dist: liblnk-python
Requires-Dist: libevtx-python
Requires-Dist: libscca-python
Requires-Dist: libregf-python
Requires-Dist: libesedb-python
Requires-Dist: libolecf-python
Requires-Dist: libfsntfs-python
Dynamic: license-file
